{
  "posts": [
    { "id": "1", "copywritten_summary": "In Devon an estimated 11,000 young people with recognised mental health disorders are not receiving support.", "charity": "Action East Devon"},
    { "id": 2, "title": "Post 2" },
    { "id": 3, "title": "Post 3" }
  ],
  "homelessness": [
    { "id": "2", "copywritten_summary": "Booth Centre is supporting the most vulnerable homeless people who are experiencing abuse, violence and or exploitation on a daily basis", "charity": "Booth Centre"}
  ]  
}
